CONTRIBUTORS.txt
LICENSE.txt
MANIFEST.in
README.textile
setup.py
django_rules/__init__.py
django_rules/backends.py
django_rules/decorators.py
django_rules/exceptions.py
django_rules/models.py
django_rules/utils.py
django_rules.egg-info/PKG-INFO
django_rules.egg-info/SOURCES.txt
django_rules.egg-info/dependency_links.txt
django_rules.egg-info/not-zip-safe
django_rules.egg-info/top_level.txt
django_rules/management/__init__.py
django_rules/management/commands/__init__.py
django_rules/management/commands/sync_rules.py
django_rules/tests/__init__.py
django_rules/tests/models.py
django_rules/tests/runtests.py
django_rules/tests/test_core.py
django_rules/tests/test_decorators.py
django_rules/tests/test_settings.py
django_rules/tests/utils.py
django_rules/tests/utils2.py
django_rules/tests/utils3.py