Metadata-Version: 1.0
Name: django-rules
Version: 0.2
Summary: Flexible per-object authorization backend for Django
Home-page: http://github.com/maraujop/django-rules
Author: Miguel Araujo
Author-email: miguel.araujo.perez@gmail.com
License: BSD
Keywords: authorization,backends,django,rules,permissions
Platform: UNKNOWN
Classifier: Programming Language :: Python
Classifier: Topic :: Software Development :: Libraries :: Python Modules
Classifier: Intended Audience :: Developers
Classifier: License :: OSI Approved :: BSD License
Classifier: Operating System :: OS Independent
Classifier: Framework :: Django
Classifier: Environment :: Web Environment
